<annotation>
	<folder>candy</folder>
	<filename>CANDY0189.png</filename>
	<path>C:\Users\Aleksandar\Desktop\yolo-groceries-dataset\dataset\images\candy\CANDY0189.png</path>
	<source>
		<database>Unknown</database>
	</source>
	<size>
		<width>224</width>
		<height>224</height>
		<depth>3</depth>
	</size>
	<segmented>0</segmented>
	<object>
		<name>candy</name>
		<pose>Unspecified</pose>
		<truncated>1</truncated>
		<difficult>0</difficult>
		<bndbox>
			<xmin>1</xmin>
			<ymin>45</ymin>
			<xmax>35</xmax>
			<ymax>160</ymax>
		</bndbox>
	</object>
	<object>
		<name>candy</name>
		<pose>Unspecified</pose>
		<truncated>0</truncated>
		<difficult>0</difficult>
		<bndbox>
			<xmin>28</xmin>
			<ymin>57</ymin>
			<xmax>108</xmax>
			<ymax>184</ymax>
		</bndbox>
	</object>
	<object>
		<name>candy</name>
		<pose>Unspecified</pose>
		<truncated>0</truncated>
		<difficult>0</difficult>
		<bndbox>
			<xmin>101</xmin>
			<ymin>63</ymin>
			<xmax>193</xmax>
			<ymax>195</ymax>
		</bndbox>
	</object>
	<object>
		<name>candy</name>
		<pose>Unspecified</pose>
		<truncated>1</truncated>
		<difficult>0</difficult>
		<bndbox>
			<xmin>184</xmin>
			<ymin>69</ymin>
			<xmax>224</xmax>
			<ymax>178</ymax>
		</bndbox>
	</object>
</annotation>
