<annotation>
	<folder>vinegar</folder>
	<filename>VINEGAR0156.png</filename>
	<path>C:\Users\antoaneta\yolo-groceries-dataset\dataset\images\vinegar\VINEGAR0156.png</path>
	<source>
		<database>Unknown</database>
	</source>
	<size>
		<width>224</width>
		<height>224</height>
		<depth>3</depth>
	</size>
	<segmented>0</segmented>
	<object>
		<name>vinegar</name>
		<pose>Unspecified</pose>
		<truncated>0</truncated>
		<difficult>0</difficult>
		<bndbox>
			<xmin>28</xmin>
			<ymin>2</ymin>
			<xmax>91</xmax>
			<ymax>209</ymax>
		</bndbox>
	</object>
	<object>
		<name>vinegar</name>
		<pose>Unspecified</pose>
		<truncated>1</truncated>
		<difficult>0</difficult>
		<bndbox>
			<xmin>88</xmin>
			<ymin>1</ymin>
			<xmax>160</xmax>
			<ymax>219</ymax>
		</bndbox>
	</object>
	<object>
		<name>vinegar</name>
		<pose>Unspecified</pose>
		<truncated>0</truncated>
		<difficult>0</difficult>
		<bndbox>
			<xmin>141</xmin>
			<ymin>16</ymin>
			<xmax>196</xmax>
			<ymax>213</ymax>
		</bndbox>
	</object>
</annotation>
