<annotation>
	<folder>coffee</folder>
	<filename>COFFEE0000.png</filename>
	<path>C:\Users\DE103463\Desktop\prj\yolo-groceries-dataset\dataset\images\coffee\COFFEE0000.png</path>
	<source>
		<database>Unknown</database>
	</source>
	<size>
		<width>224</width>
		<height>224</height>
		<depth>3</depth>
	</size>
	<segmented>0</segmented>
	<object>
		<name>chocolate</name>
		<pose>Unspecified</pose>
		<truncated>0</truncated>
		<difficult>0</difficult>
		<bndbox>
			<xmin>38</xmin>
			<ymin>95</ymin>
			<xmax>144</xmax>
			<ymax>185</ymax>
		</bndbox>
	</object>
	<object>
		<name>chocolate</name>
		<pose>Unspecified</pose>
		<truncated>1</truncated>
		<difficult>0</difficult>
		<bndbox>
			<xmin>143</xmin>
			<ymin>102</ymin>
			<xmax>224</xmax>
			<ymax>203</ymax>
		</bndbox>
	</object>
	<object>
		<name>chocolate</name>
		<pose>Unspecified</pose>
		<truncated>1</truncated>
		<difficult>0</difficult>
		<bndbox>
			<xmin>1</xmin>
			<ymin>13</ymin>
			<xmax>90</xmax>
			<ymax>94</ymax>
		</bndbox>
	</object>
</annotation>
