<annotation>
	<folder>tomato_sauce</folder>
	<filename>TOMATO_SAUCE0138.png</filename>
	<path>C:\Users\Aleksandar\Desktop\groceries-object-detection-dataset\dataset\images\tomato_sauce\TOMATO_SAUCE0138.png</path>
	<source>
		<database>Unknown</database>
	</source>
	<size>
		<width>224</width>
		<height>224</height>
		<depth>3</depth>
	</size>
	<segmented>0</segmented>
	<object>
		<name>tomato_sauce</name>
		<pose>Unspecified</pose>
		<truncated>0</truncated>
		<difficult>0</difficult>
		<bndbox>
			<xmin>78</xmin>
			<ymin>32</ymin>
			<xmax>164</xmax>
			<ymax>109</ymax>
		</bndbox>
	</object>
	<object>
		<name>tomato_sauce</name>
		<pose>Unspecified</pose>
		<truncated>0</truncated>
		<difficult>0</difficult>
		<bndbox>
			<xmin>11</xmin>
			<ymin>61</ymin>
			<xmax>91</xmax>
			<ymax>113</ymax>
		</bndbox>
	</object>
	<object>
		<name>tomato_sauce</name>
		<pose>Unspecified</pose>
		<truncated>0</truncated>
		<difficult>0</difficult>
		<bndbox>
			<xmin>122</xmin>
			<ymin>115</ymin>
			<xmax>183</xmax>
			<ymax>167</ymax>
		</bndbox>
	</object>
</annotation>
